pyecon/__init__.py
pyecon-0.1.2.dist-info/LICENSE
pyecon-0.1.2.dist-info/WHEEL
pyecon-0.1.2.dist-info/METADATA
pyecon-0.1.2.dist-info/RECORD
